Metadata-Version: 1.2
Name: Flask-Philo-PynamoDB
Version: 0.1.0
Summary: Flask-Philo plugin that provides support for PynamoDB
Home-page: https://github.com/Riffstation/Flask-Philo-PynamoDB
Author: Manuel Ignacio Franco Galeano
Author-email: maigfrga@gmail.com
License: Apache
Keywords: FLASK AWS DynamoDB
Platform: UNKNOWN
Classifier: Development Status :: 4 - Beta
Classifier: Intended Audience :: Developers
Classifier: Topic :: Software Development
Classifier: Framework :: Flask
Classifier: Programming Language :: Python :: 3
Requires-Python: >=3.6
